<?xml version='1.0' encoding='UTF-8'?>
<vdb name="JoinTestVDB" version="1">


<model name="views" type="VIRTUAL">
<metadata type="DDL">
<![CDATA[CREATE VIEW JoinTestView (
	RowId integer,
	SUPPLIER_ID string,
	PART_ID string,
	QUANTITY bigdecimal,
	SHIPPER_ID bigdecimal,
	PART_NAME string,
	PART_COLOR string,
	PART_WEIGHT string,
	PRIMARY KEY(RowId)
)
AS
SELECT ROW_NUMBER() OVER (ORDER BY A.SUPPLIER_ID), A.SUPPLIER_ID, A.PART_ID, A.QUANTITY, A.SHIPPER_ID, B.PART_NAME, B.PART_COLOR, B.PART_WEIGHT FROM SUPPLIER_PARTS AS A INNER JOIN PARTS AS B ON A.PART_ID = B.PART_ID;
]]>

</metadata>
</model>
<model name="OraclePartsDB" type="PHYSICAL">
<source name="PartsOracle" translator-name="oracle" connection-jndi-name="java:/PartsOracle"/>
<metadata type="DDL">
<![CDATA[CREATE FOREIGN TABLE SUPPLIER_PARTS (
	SUPPLIER_ID string(10) NOT NULL OPTIONS ("NAMEINSOURCE" '"SUPPLIER_ID"', "NATIVE_TYPE" 'VARCHAR2'),
	PART_ID string(4) NOT NULL OPTIONS ("NAMEINSOURCE" '"PART_ID"', "NATIVE_TYPE" 'CHAR'),
	QUANTITY bigdecimal(3) OPTIONS ("NAMEINSOURCE" '"QUANTITY"', "NATIVE_TYPE" 'NUMBER', "CHAR_OCTET_LENGTH" '22'),
	SHIPPER_ID bigdecimal(2) OPTIONS ("NAMEINSOURCE" '"SHIPPER_ID"', "NATIVE_TYPE" 'NUMBER', "CHAR_OCTET_LENGTH" '22')
) OPTIONS ("UPDATABLE" 'TRUE', "NAMEINSOURCE" '"SUPPLIER_PARTS"', "CARDINALITY" '212');

CREATE FOREIGN TABLE PARTS (
	PART_ID string(4) NOT NULL OPTIONS ("NAMEINSOURCE" '"PART_ID"', "NATIVE_TYPE" 'CHAR'),
	PART_NAME string(255) OPTIONS ("NAMEINSOURCE" '"PART_NAME"', "NATIVE_TYPE" 'VARCHAR2'),
	PART_COLOR string(30) OPTIONS ("NAMEINSOURCE" '"PART_COLOR"', "NATIVE_TYPE" 'VARCHAR2'),
	PART_WEIGHT string(255) OPTIONS ("NAMEINSOURCE" '"PART_WEIGHT"', "NATIVE_TYPE" 'VARCHAR2')
) OPTIONS ("UPDATABLE" 'TRUE', "NAMEINSOURCE" '"PARTS"', "CARDINALITY" '17');
]]>

</metadata>
</model>

</vdb>